{
  "global": {
    "tipo": "cancion",
    "data": {
      "partes": [
        {
          "id": "f6cec2f2-28d8-4a78-b9c6-fb514addc4ad",
          "cancion_id": "033f94b6-26fb-4b7a-aa14-b6d1426ab3ce",
          "tipo": "Verso",
          "texto": "LUZ DE VIDA CELESTIAL,\nFUEGO DE DIVINO AMOR,\nBRILLA EN MI CORAZÓN,\nVEN, INSPÍRAME FERVOR.\nA CANTAR AYÚDAME\nDIGNAMENTE EN HONOR\nDEL CORDERO QUE MURIÓ\nPOR SALVAR AL PECADOR",
          "orden": 0,
          "texto_letra": "LUZ DE VIDA CELESTIAL,\nFUEGO DE DIVINO AMOR,\nBRILLA EN MI CORAZÓN,\nVEN, INSPÍRAME FERVOR.\nA CANTAR AYÚDAME\nDIGNAMENTE EN HONOR\nDEL CORDERO QUE MURIÓ\nPOR SALVAR AL PECADOR",
          "texto_acordes": null,
          "tiene_acordes": false
        },
        {
          "id": "7be8c05c-ad03-4519-871f-dcc03dfe56a4",
          "cancion_id": "033f94b6-26fb-4b7a-aa14-b6d1426ab3ce",
          "tipo": "Verso",
          "texto": "DIGNO, DIGNO DE HONOR\nES MI REDENTO JESÚS,\nQUIEN AL MUNDO REDIMIÓ\nPOR SU MUERTE EN LA CRUZ.\nGLORIA SEA A JESÚS,\nGLORIA SEA Y LOOR,\nY DOMINIO ETERNAL\nA JESÚS, MI REDENTOR.",
          "orden": 1,
          "texto_letra": "DIGNO, DIGNO DE HONOR\nES MI REDENTO JESÚS,\nQUIEN AL MUNDO REDIMIÓ\nPOR SU MUERTE EN LA CRUZ.\nGLORIA SEA A JESÚS,\nGLORIA SEA Y LOOR,\nY DOMINIO ETERNAL\nA JESÚS, MI REDENTOR.",
          "texto_acordes": null,
          "tiene_acordes": false
        }
      ],
      "index": 1,
      "titulo": "LUZ DE VIDA",
      "tono": "Re",
      "iglesia": "IEP Moradora de Sion La Ligua",
      "logo_marca_url": "https://dkufqtrfvduonsubmwka.supabase.co/storage/v1/object/public/imagenes-culto/logos/c76bc168-da61-4a86-8881-9dc3c17391fe/1778514807728-hc7u8bqcy5o.png",
      "fondo": {
        "tipo": "preset",
        "preset": "cielo-dorado",
        "fondoCss": "radial-gradient(circle at 50% 20%, rgba(251,191,36,0.45), transparent 34%), linear-gradient(135deg, #1e1b4b 0%, #7c2d12 48%, #0f172a 100%)",
        "nombre": "Cielo dorado",
        "oscuridad": 55,
        "ajuste": "cover"
      }
    }
  },
  "9c6246da-b5bb-449a-b283-13dd465b46d2": {
    "tipo": "cancion",
    "data": {
      "partes": [
        {
          "id": "f6cec2f2-28d8-4a78-b9c6-fb514addc4ad",
          "cancion_id": "033f94b6-26fb-4b7a-aa14-b6d1426ab3ce",
          "tipo": "Verso",
          "texto": "LUZ DE VIDA CELESTIAL,\nFUEGO DE DIVINO AMOR,\nBRILLA EN MI CORAZÓN,\nVEN, INSPÍRAME FERVOR.\nA CANTAR AYÚDAME\nDIGNAMENTE EN HONOR\nDEL CORDERO QUE MURIÓ\nPOR SALVAR AL PECADOR",
          "orden": 0,
          "texto_letra": "LUZ DE VIDA CELESTIAL,\nFUEGO DE DIVINO AMOR,\nBRILLA EN MI CORAZÓN,\nVEN, INSPÍRAME FERVOR.\nA CANTAR AYÚDAME\nDIGNAMENTE EN HONOR\nDEL CORDERO QUE MURIÓ\nPOR SALVAR AL PECADOR",
          "texto_acordes": null,
          "tiene_acordes": false
        },
        {
          "id": "7be8c05c-ad03-4519-871f-dcc03dfe56a4",
          "cancion_id": "033f94b6-26fb-4b7a-aa14-b6d1426ab3ce",
          "tipo": "Verso",
          "texto": "DIGNO, DIGNO DE HONOR\nES MI REDENTO JESÚS,\nQUIEN AL MUNDO REDIMIÓ\nPOR SU MUERTE EN LA CRUZ.\nGLORIA SEA A JESÚS,\nGLORIA SEA Y LOOR,\nY DOMINIO ETERNAL\nA JESÚS, MI REDENTOR.",
          "orden": 1,
          "texto_letra": "DIGNO, DIGNO DE HONOR\nES MI REDENTO JESÚS,\nQUIEN AL MUNDO REDIMIÓ\nPOR SU MUERTE EN LA CRUZ.\nGLORIA SEA A JESÚS,\nGLORIA SEA Y LOOR,\nY DOMINIO ETERNAL\nA JESÚS, MI REDENTOR.",
          "texto_acordes": null,
          "tiene_acordes": false
        }
      ],
      "index": 0,
      "titulo": "LUZ DE VIDA",
      "tono": "Re",
      "iglesia": "",
      "fondo": {
        "tipo": "preset",
        "preset": "purpura-noche",
        "fondoCss": "radial-gradient(circle at 20% 30%, rgba(168,85,247,0.38), transparent 32%), radial-gradient(circle at 85% 65%, rgba(236,72,153,0.28), transparent 32%), linear-gradient(135deg, #020617 0%, #312e81 52%, #581c87 100%)",
        "nombre": "Púrpura noche",
        "oscuridad": 55,
        "ajuste": "cover"
      }
    }
  },
  "cb7db0f2-7e9a-4cb7-bdfb-2bdd57ca1630": {
    "tipo": "cancion",
    "data": {
      "partes": [
        {
          "id": "09fb3d3f-5953-4307-913f-0ee6611a5f75",
          "cancion_id": "e5a414bd-f427-4525-9e9d-00c471fe5be6",
          "tipo": "Verso",
          "texto": "VEN, ¡OH, TODOPODEROSO,\nADORABLE CREADOR!\nPADRE SANTO, CARIÑOSO,\nMANIFIESTA TU AMOR.\nA TU TRONO DE CLEMENCIA\nLEVANTAMOS NUESTRA VOZ.\nTU PRESENCIA TE PEDIMOS,\nNUESTRO PADRE, NUESTRO DIOS.",
          "orden": 0,
          "texto_letra": "VEN, ¡OH, TODOPODEROSO,\nADORABLE CREADOR!\nPADRE SANTO, CARIÑOSO,\nMANIFIESTA TU AMOR.\nA TU TRONO DE CLEMENCIA\nLEVANTAMOS NUESTRA VOZ.\nTU PRESENCIA TE PEDIMOS,\nNUESTRO PADRE, NUESTRO DIOS.",
          "texto_acordes": null,
          "tiene_acordes": false
        },
        {
          "id": "10c26dca-a27f-49d3-a877-eef2b22589b6",
          "cancion_id": "e5a414bd-f427-4525-9e9d-00c471fe5be6",
          "tipo": "Verso",
          "texto": "VEN, ¡OH SALVADOR DIVINO,\nDIOS DE NUESTRA SALVACIÓN!\nEN NOSOTROS HAZ MORADA,\nVIVE EN NUESTRO CORAZÓN.\nERES TÚ, JESÚS, BENIGNO,\nERES INFINITO AMOR:\nÓYENOS, TE SUPLICAMOS.\nVEN, BENDÍCENOS, SEÑOR.",
          "orden": 1,
          "texto_letra": "VEN, ¡OH SALVADOR DIVINO,\nDIOS DE NUESTRA SALVACIÓN!\nEN NOSOTROS HAZ MORADA,\nVIVE EN NUESTRO CORAZÓN.\nERES TÚ, JESÚS, BENIGNO,\nERES INFINITO AMOR:\nÓYENOS, TE SUPLICAMOS.\nVEN, BENDÍCENOS, SEÑOR.",
          "texto_acordes": null,
          "tiene_acordes": false
        },
        {
          "id": "f83130fb-8fb4-4fdf-b59e-d63b48fa083e",
          "cancion_id": "e5a414bd-f427-4525-9e9d-00c471fe5be6",
          "tipo": "Verso",
          "texto": "VEN, ¡ESPÍRITU DIVINO!\nDANOS TU PRECIOSO DON;\nDIOS CONSOLADOR, INSPIRA\nPAZ EN TODO CORAZÓN.\nDE LOS SANTOS LA HERENCIA\nDÉJANOS HALLAR EN TI.\nY LA VIDA DE LOS CIELOS\nGOZAREMOS YA AQUÍ.",
          "orden": 2,
          "texto_letra": "VEN, ¡ESPÍRITU DIVINO!\nDANOS TU PRECIOSO DON;\nDIOS CONSOLADOR, INSPIRA\nPAZ EN TODO CORAZÓN.\nDE LOS SANTOS LA HERENCIA\nDÉJANOS HALLAR EN TI.\nY LA VIDA DE LOS CIELOS\nGOZAREMOS YA AQUÍ.",
          "texto_acordes": null,
          "tiene_acordes": false
        }
      ],
      "index": 0,
      "titulo": "VEN, ¡OH, TODOPODEROSO",
      "tono": "Sol",
      "iglesia": "IEP Moradora de Sion Renca",
      "logo_marca_url": "https://dkufqtrfvduonsubmwka.supabase.co/storage/v1/object/public/imagenes-culto/logos/cb7db0f2-7e9a-4cb7-bdfb-2bdd57ca1630/1778516783046-kbg9fygymg.png",
      "fondo": {
        "tipo": "estatico",
        "url": "https://dkufqtrfvduonsubmwka.supabase.co/storage/v1/object/public/imagenes-culto/1779371052551-xmna7dff33g.webp",
        "nombre": "WhatsApp Image 2026-05-18 at 19.55.07 (2)",
        "oscuridad": 55,
        "ajuste": "cover"
      }
    }
  },
  "c76bc168-da61-4a86-8881-9dc3c17391fe": {
    "tipo": "cancion",
    "data": {
      "partes": [
        {
          "id": "9830c4c1-6970-47b9-9346-cc54cd6a36b1",
          "cancion_id": "be2562af-7831-4ff5-aa32-9a9a1a4eee1c",
          "tipo": "Verso",
          "texto": "VOY AL CIELO -SOY PEREGRINO-\nA VIVIR ETERNAMENTE CON JESÚS,\nEL NOS ABRIÓ, YA, VERAZ CAMINO,\nCUANDO MURIÓ POR NOSOTROS EN LA CRUZ.",
          "orden": 0,
          "texto_letra": "VOY AL CIELO -SOY PEREGRINO-\nA VIVIR ETERNAMENTE CON JESÚS,\nEL NOS ABRIÓ, YA, VERAZ CAMINO,\nCUANDO MURIÓ POR NOSOTROS EN LA CRUZ.",
          "texto_acordes": "2 Timoteo 1.12 2 Corintios 5.1 Salmo 17.15",
          "tiene_acordes": true
        },
        {
          "id": "d4750c7c-dab1-4edf-8f2a-36ff09495486",
          "cancion_id": "be2562af-7831-4ff5-aa32-9a9a1a4eee1c",
          "tipo": "Coro",
          "texto": "VOY AL CIELO -SOY PEREGRINO-\nA VIVIR ETERNAMENTE CON JESÚS.",
          "orden": 1,
          "texto_letra": "VOY AL CIELO -SOY PEREGRINO-\nA VIVIR ETERNAMENTE CON JESÚS.",
          "texto_acordes": "E\nAl cielo voy, al cielo voy,",
          "tiene_acordes": true
        },
        {
          "id": "dd2f346b-07a8-4c6f-a20f-59cb1bc4024e",
          "cancion_id": "be2562af-7831-4ff5-aa32-9a9a1a4eee1c",
          "tipo": "Verso",
          "texto": "MUERTE, DUELOS, AMARGA PENA,\nNUNCA, NUNCA SE PODRÁN SENTIR MÁS ALLÁ,\nPRECIOSA VIDA DE GOZO LLENA,\nEL ALMA MÍA SIN FIN DISFRUTARÁ.",
          "orden": 2,
          "texto_letra": "MUERTE, DUELOS, AMARGA PENA,\nNUNCA, NUNCA SE PODRÁN SENTIR MÁS ALLÁ,\nPRECIOSA VIDA DE GOZO LLENA,\nEL ALMA MÍA SIN FIN DISFRUTARÁ.",
          "texto_acordes": "B              E\nyo confío en Jesús.",
          "tiene_acordes": true
        },
        {
          "id": "9450104d-8980-4c6e-ac5b-ae716caf7fee",
          "cancion_id": "be2562af-7831-4ff5-aa32-9a9a1a4eee1c",
          "tipo": "Verso",
          "texto": "TIERRA SANTA, HERMOSA Y PURA,\nENTRARÉ A TI, SALVADO POR JESÚS;\nY GOZARÉ CÉLICA VENTURA\nVIVIENDO SIEMPRE EN LA DIVINA LUZ.",
          "orden": 3,
          "texto_letra": "TIERRA SANTA, HERMOSA Y PURA,\nENTRARÉ A TI, SALVADO POR JESÚS;\nY GOZARÉ CÉLICA VENTURA\nVIVIENDO SIEMPRE EN LA DIVINA LUZ.",
          "texto_acordes": "E\nÉl me salvó, Él me salvó;",
          "tiene_acordes": true
        }
      ],
      "index": 3,
      "titulo": "VOY AL CIELO",
      "tono": "Re",
      "iglesia": "IEP Moradora de Sion La Ligua",
      "logo_marca_url": "https://dkufqtrfvduonsubmwka.supabase.co/storage/v1/object/public/imagenes-culto/logos/c76bc168-da61-4a86-8881-9dc3c17391fe/1778514807728-hc7u8bqcy5o.png",
      "fondo": {
        "tipo": "preset",
        "preset": "cielo-dorado",
        "fondoCss": "radial-gradient(circle at 50% 20%, rgba(251,191,36,0.45), transparent 34%), linear-gradient(135deg, #1e1b4b 0%, #7c2d12 48%, #0f172a 100%)",
        "nombre": "Cielo dorado",
        "oscuridad": 55,
        "ajuste": "cover"
      }
    }
  }
}